{
    "DEVICE": {
        "disabled" : false,
        "binary": "app-device-config-no-hfxo.json",
        "version" : "1.0.0",
        "signed": false
    },
    "A32_DBG": {
        "disabled": true,
        "binary": "a32_stub_0.bin",
        "version" : "1.0.0",
        "signed": false,
        "loadAddress": "0x02000000",
        "cpu_id": "A32_0",
        "flags": ["load","boot"]
    },
    "HP_DBG": {
        "disabled": true,
        "binary": "m55_stub_hp.bin",
        "version" : "1.0.0",
        "signed": false,
        "loadAddress": "0x50000000",
        "cpu_id": "M55_HP",
        "flags": ["load","boot"]
    },
    "HE_DBG": {
        "disabled": false,
        "binary": "m55_stub_he.bin",
        "version" : "1.0.0",
        "signed": false,
        "loadAddress": "0x58000000",
        "cpu_id": "M55_HE",
        "flags": ["load", "boot"]
    }
}
